pito/__init__.py
pito/main.py
pito/builtin/__init__.py
pito/builtin/base.py
pito/template/config.yaml
pito/template/header.pto
pito/template/main.pdf
pito/template/main.pto
pito/template/components/nested_example.pto
pito/template/components/testfile.pto
pito/template/fn/main_fn.py
pito-0.1.1.dist-info/METADATA
pito-0.1.1.dist-info/WHEEL
pito-0.1.1.dist-info/entry_points.txt
pito-0.1.1.dist-info/top_level.txt
pito-0.1.1.dist-info/RECORD
