Metadata-Version: 2.4
Name: pito
Version: 0.1.1
Summary: Pito: A lightweight dynamic programatically static pdf document generator.
Author-email: Shinapri <shinapri.2003.1@gmail.com>
Classifier: Programming Language :: Python :: 3
Classifier: License :: OSI Approved :: MIT License
Classifier: Operating System :: OS Independent
Requires-Python: >=3.9
Requires-Dist: PyYAML
